graphtask/__init__.py
graphtask/_check.py
graphtask/_task.py
graphtask-0.0.1.dist-info/LICENSE
graphtask-0.0.1.dist-info/WHEEL
graphtask-0.0.1.dist-info/METADATA
graphtask-0.0.1.dist-info/RECORD
