Metadata-Version: 2.1
Name: graphtask
Version: 0.0.1
Summary: Build implicit task graphs from functions and process them in parallel.
Home-page: https://github.com/davnn/graphtask
License: MIT
Author: David Muhr
Author-email: muhrdavid+github@gmail.com
Requires-Python: >=3.9,<4.0
Classifier: Development Status :: 3 - Alpha
Classifier: Intended Audience :: Developers
Classifier: Intended Audience :: Education
Classifier: Intended Audience :: Science/Research
Classifier: License :: OSI Approved :: MIT License
Classifier: Operating System :: MacOS
Classifier: Operating System :: Microsoft :: Windows
Classifier: Operating System :: POSIX
Classifier: Operating System :: Unix
Classifier: Programming Language :: Python :: 3
Classifier: Programming Language :: Python :: 3.9
Classifier: Programming Language :: Python :: 3.10
Classifier: Programming Language :: Python :: 3.11
Classifier: Programming Language :: Python :: 3 :: Only
Classifier: Programming Language :: Python :: 3.10
Classifier: Programming Language :: Python :: 3.11
Classifier: Programming Language :: Python :: 3.9
Classifier: Topic :: Scientific/Engineering
Classifier: Topic :: Software Development :: Libraries
Classifier: Topic :: Utilities
Classifier: Typing :: Typed
Provides-Extra: visualize
Requires-Dist: joblib (>=1.1.1,<2.0.0)
Requires-Dist: networkx (>=2.8.7,<3.0.0)
Requires-Dist: pygraphviz (==1.10); extra == "visualize"
Requires-Dist: stackeddag (>=0.3.3,<0.4.0)
Project-URL: Repository, https://github.com/davnn/graphtask
